appuio_routes_monitoring/__init__.py
appuio_routes_monitoring/__main__.py
appuio_routes_monitoring/generate_monitoring_check.py
appuio_routes_monitoring-1.2.1.dist-info/LICENCE
appuio_routes_monitoring-1.2.1.dist-info/METADATA
appuio_routes_monitoring-1.2.1.dist-info/WHEEL
appuio_routes_monitoring-1.2.1.dist-info/entry_points.txt
appuio_routes_monitoring-1.2.1.dist-info/top_level.txt
appuio_routes_monitoring-1.2.1.dist-info/RECORD
