Metadata-Version: 2.1
Name: appuio-routes-monitoring
Version: 1.2.1
Summary: A tool to generate yaml code for hieradata from APPUiO routes to configure
Home-page: https://git.vshn.net/vshn/appuio_routes_monitoring
Author: Nicolas Bigler
Author-email: nicolas.bigler@vshn.ch
License: BSD
Platform: any
Classifier: Development Status :: 4 - Beta
Classifier: Environment :: Console
Classifier: Intended Audience :: System Administrators
Classifier: License :: OSI Approved :: BSD License
Classifier: Operating System :: Unix
Classifier: Programming Language :: Python :: 3 :: Only
Classifier: Topic :: System :: Systems Administration
Requires-Python: >=3.5
Requires-Dist: pyyaml
